human_rag/__init__.py
human_rag/py.typed
human_rag-0.0.1.dev0.dist-info/METADATA
human_rag-0.0.1.dev0.dist-info/WHEEL
human_rag-0.0.1.dev0.dist-info/RECORD
