Metadata-Version: 2.4
Name: human-rag
Version: 0.0.1.dev0
Summary: A RAG system that operates like a human
Author-email: Gus <contact@memobase.io>
Requires-Python: >=3.11
Requires-Dist: openai>=1.75.0
Requires-Dist: pydantic>=2.11.3
